hsfiles_jupyter/__init__.py
hsfiles_jupyter/__main__.py
hsfiles_jupyter/_version.py
hsfiles_jupyter/check_file_status.py
hsfiles_jupyter/delete_file.py
hsfiles_jupyter/download_file.py
hsfiles_jupyter/handlers.py
hsfiles_jupyter/refresh_file.py
hsfiles_jupyter/upload_file.py
hsfiles_jupyter/utils.py
hsfiles_jupyter/labextension/package.json
hsfiles_jupyter/labextension/static/458.3bd4979eca4992cbb3bb.js
hsfiles_jupyter/labextension/static/remoteEntry.d6235c2cac229fbe3083.js
hsfiles_jupyter/labextension/static/style.js
hsfiles_jupyter/labextension/static/third-party-licenses.json
hsfiles_jupyter-0.2.1.data/data/etc/jupyter/jupyter_server_config.d/hsfiles_jupyter.json
hsfiles_jupyter-0.2.1.dist-info/licenses/LICENSE
hsfiles_jupyter-0.2.1.dist-info/METADATA
hsfiles_jupyter-0.2.1.dist-info/WHEEL
hsfiles_jupyter-0.2.1.dist-info/top_level.txt
hsfiles_jupyter-0.2.1.dist-info/RECORD
