Metadata-Version: 2.4
Name: hsfiles_jupyter
Version: 0.2.1
Summary: A JupyterLab extension to manage HydroShare resource files in JupyterLab
Home-page: https://github.com/hydroshare/hsfiles_jupyter
Author: Pabitra Dash
Author-email: pabitra.dash@usu.edu
License: BSD-3-Clause
Classifier: Development Status :: 4 - Beta
Classifier: Programming Language :: Python :: 3
Classifier: Programming Language :: Python :: 3.8
Classifier: Programming Language :: Python :: 3.9
Classifier: Programming Language :: Python :: 3.10
Requires-Python: >=3.9
License-File: LICENSE
Requires-Dist: hsclient>=1.1.6
Requires-Dist: jupyterlab==4.3.*
Requires-Dist: jupyter_server<3,>=2.13
Provides-Extra: dev
Requires-Dist: build; extra == "dev"
Requires-Dist: setuptools; extra == "dev"
Requires-Dist: wheel; extra == "dev"
Requires-Dist: twine; extra == "dev"
Requires-Dist: pytest; extra == "dev"
Requires-Dist: pytest-asyncio; extra == "dev"
Requires-Dist: asynctest; extra == "dev"
Requires-Dist: tornado; extra == "dev"
Dynamic: author
Dynamic: author-email
Dynamic: classifier
Dynamic: description
Dynamic: description-content-type
Dynamic: home-page
Dynamic: license
Dynamic: license-file
Dynamic: provides-extra
Dynamic: requires-dist
Dynamic: requires-python
Dynamic: summary
